parse_tools/db_manager.py
parse_tools/get_conclusion.py
parse_tools/get_contrast.py
parse_tools/get_scene_report.py
parse_tools/globalVal.py
parse_tools/manual_perform_parse.py
parse_tools/parseAudioStreamPerfom.py
parse_tools/read_message.py
parse_tools/speech_parse.py
parse_tools/stream_perform_parse.py
parse_tools/wer_client.py
parse_tools/xls.py
parse_tools-1.0.0.dist-info/METADATA
parse_tools-1.0.0.dist-info/WHEEL
parse_tools-1.0.0.dist-info/top_level.txt
parse_tools-1.0.0.dist-info/RECORD
