Metadata-Version: 2.1
Name: parse-tools
Version: 1.0.0
Summary: A stream performance data parse tools for PyPI
Home-page: https://www.python.org/
Author: dushuangshuang
Author-email: shuang2du@163.com
License: MIT
Project-URL: Documentation, https://packaging.python.org
Project-URL: Funding, https://donate.pypi.org
Project-URL: Source, https://github.com
Project-URL: Tracker, https://github.com
Keywords: POPpin008366
Platform: UNKNOWN
Requires-Python: >=3
Requires-Dist: numpy (>=1.14)
Requires-Dist: tensorflow (>=1.7)
